AUTHORS
ChangeLog
LICENSE
MANIFEST.in
README.rst
requirements.txt
setup.cfg
setup.py
leonardo_multisite/__init__.py
leonardo_multisite/middleware.py
leonardo_multisite/models.py
leonardo_multisite/settings.py
leonardo_multisite.egg-info/PKG-INFO
leonardo_multisite.egg-info/SOURCES.txt
leonardo_multisite.egg-info/dependency_links.txt
leonardo_multisite.egg-info/not-zip-safe
leonardo_multisite.egg-info/pbr.json
leonardo_multisite.egg-info/requires.txt
leonardo_multisite.egg-info/top_level.txt